materials_for_mc-0.2.0.dist-info/METADATA
materials_for_mc-0.2.0.dist-info/WHEEL
materials_for_mc/__init__.py
materials_for_mc/materials_for_mc.cp312-win_amd64.pyd
materials_for_mc-0.2.0.dist-info/RECORD
