Metadata-Version: 2.4
Name: materials_for_mc
Version: 0.2.0
Summary: Material builder for Monte Carlo simulations
License: MIT
